[{"tag":"RELABEL","start1":22122,"end1":22136,"segments1":[{"start":22122,"end":22136}],"start2":22178,"end2":22196,"segments2":[{"start":22178,"end":22196}]},{"tag":"RELABEL","start1":18250,"end1":18264,"segments1":[{"start":18250,"end":18264}],"start2":18302,"end2":18320,"segments2":[{"start":18302,"end":18320}]},{"tag":"RELABEL","start1":18212,"end1":18226,"segments1":[{"start":18212,"end":18226}],"start2":18260,"end2":18278,"segments2":[{"start":18260,"end":18278}]},{"tag":"RELABEL","start1":12974,"end1":12988,"segments1":[{"start":12974,"end":12988}],"start2":13018,"end2":13036,"segments2":[{"start":13018,"end":13036}]},{"tag":"RELABEL","start1":12936,"end1":12950,"segments1":[{"start":12936,"end":12950}],"start2":12976,"end2":12994,"segments2":[{"start":12976,"end":12994}]},{"tag":"RELABEL","start1":9004,"end1":9018,"segments1":[{"start":9004,"end":9018}],"start2":9040,"end2":9058,"segments2":[{"start":9040,"end":9058}]},{"tag":"RELABEL","start1":8966,"end1":8980,"segments1":[{"start":8966,"end":8980}],"start2":8998,"end2":9016,"segments2":[{"start":8998,"end":9016}]},{"tag":"RELABEL","start1":7885,"end1":7899,"segments1":[{"start":7885,"end":7899}],"start2":7913,"end2":7931,"segments2":[{"start":7913,"end":7931}]},{"tag":"RELABEL","start1":7847,"end1":7861,"segments1":[{"start":7847,"end":7861}],"start2":7871,"end2":7889,"segments2":[{"start":7871,"end":7889}]},{"tag":"RELABEL","start1":5936,"end1":5950,"segments1":[{"start":5936,"end":5950}],"start2":5956,"end2":5974,"segments2":[{"start":5956,"end":5974}]},{"tag":"RELABEL","start1":5898,"end1":5912,"segments1":[{"start":5898,"end":5912}],"start2":5914,"end2":5932,"segments2":[{"start":5914,"end":5932}]},{"tag":"RELABEL","start1":3985,"end1":3999,"segments1":[{"start":3985,"end":3999}],"start2":3997,"end2":4015,"segments2":[{"start":3997,"end":4015}]},{"tag":"RELABEL","start1":3947,"end1":3961,"segments1":[{"start":3947,"end":3961}],"start2":3955,"end2":3973,"segments2":[{"start":3955,"end":3973}]},{"tag":"RELABEL","start1":2810,"end1":2824,"segments1":[{"start":2810,"end":2824}],"start2":2814,"end2":2832,"segments2":[{"start":2814,"end":2832}]},{"tag":"RELABEL","start1":2772,"end1":2786,"segments1":[{"start":2772,"end":2786}],"start2":2772,"end2":2790,"segments2":[{"start":2772,"end":2790}]},{"tag":"IGNORED1","segments1":[{"start":2214,"end":2244}]},{"tag":"IGNORED1","segments1":[{"start":2584,"end":2612}]},{"tag":"IGNORED1","segments1":[{"start":3157,"end":3173}]},{"tag":"IGNORED1","segments1":[{"start":3573,"end":3601}]},{"tag":"IGNORED1","segments1":[{"start":4313,"end":4376}]},{"tag":"IGNORED1","segments1":[{"start":4388,"end":4435}]},{"tag":"IGNORED1","segments1":[{"start":5286,"end":5302}]},{"tag":"IGNORED1","segments1":[{"start":5710,"end":5738}]},{"tag":"IGNORED1","segments1":[{"start":6264,"end":6327}]},{"tag":"IGNORED1","segments1":[{"start":6339,"end":6386}]},{"tag":"IGNORED1","segments1":[{"start":7237,"end":7253}]},{"tag":"IGNORED1","segments1":[{"start":7656,"end":7684}]},{"tag":"IGNORED1","segments1":[{"start":8235,"end":8251}]},{"tag":"IGNORED1","segments1":[{"start":8662,"end":8690}]},{"tag":"IGNORED1","segments1":[{"start":9333,"end":9349}]},{"tag":"IGNORED1","segments1":[{"start":9406,"end":9436}]},{"tag":"IGNORED1","segments1":[{"start":9790,"end":9818}]},{"tag":"IGNORED1","segments1":[{"start":10234,"end":10256}]},{"tag":"IGNORED1","segments1":[{"start":11083,"end":11107}]},{"tag":"IGNORED1","segments1":[{"start":11407,"end":11444}]},{"tag":"IGNORED1","segments1":[{"start":11542,"end":11570}]},{"tag":"IGNORED1","segments1":[{"start":12435,"end":12445}]},{"tag":"IGNORED1","segments1":[{"start":13460,"end":13504}]},{"tag":"IGNORED1","segments1":[{"start":13725,"end":13741}]},{"tag":"IGNORED1","segments1":[{"start":14352,"end":14374}]},{"tag":"IGNORED1","segments1":[{"start":14579,"end":14609}]},{"tag":"IGNORED1","segments1":[{"start":14955,"end":14983}]},{"tag":"IGNORED1","segments1":[{"start":15399,"end":15421}]},{"tag":"IGNORED1","segments1":[{"start":16109,"end":16133}]},{"tag":"IGNORED1","segments1":[{"start":16433,"end":16470}]},{"tag":"IGNORED1","segments1":[{"start":16568,"end":16596}]},{"tag":"IGNORED1","segments1":[{"start":17776,"end":17786}]},{"tag":"IGNORED1","segments1":[{"start":18736,"end":18780}]},{"tag":"IGNORED1","segments1":[{"start":19001,"end":19017}]},{"tag":"IGNORED1","segments1":[{"start":19356,"end":19378}]},{"tag":"IGNORED1","segments1":[{"start":19661,"end":19704}]},{"tag":"IGNORED1","segments1":[{"start":21190,"end":21217}]},{"tag":"IGNORED1","segments1":[{"start":24207,"end":24218}]},{"tag":"IGNORED1","segments1":[{"start":24423,"end":24456}]},{"tag":"IGNORED1","segments1":[{"start":24610,"end":24668}]},{"tag":"IGNORED1","segments1":[{"start":24783,"end":24807}]},{"tag":"IGNORED1","segments1":[{"start":25060,"end":25085}]},{"tag":"IGNORED2","segments2":[{"start":2214,"end":2244}]},{"tag":"IGNORED2","segments2":[{"start":2584,"end":2612}]},{"tag":"IGNORED2","segments2":[{"start":3165,"end":3181}]},{"tag":"IGNORED2","segments2":[{"start":3581,"end":3609}]},{"tag":"IGNORED2","segments2":[{"start":4329,"end":4392}]},{"tag":"IGNORED2","segments2":[{"start":4404,"end":4451}]},{"tag":"IGNORED2","segments2":[{"start":5302,"end":5318}]},{"tag":"IGNORED2","segments2":[{"start":5726,"end":5754}]},{"tag":"IGNORED2","segments2":[{"start":6288,"end":6351}]},{"tag":"IGNORED2","segments2":[{"start":6363,"end":6410}]},{"tag":"IGNORED2","segments2":[{"start":7261,"end":7277}]},{"tag":"IGNORED2","segments2":[{"start":7680,"end":7708}]},{"tag":"IGNORED2","segments2":[{"start":8267,"end":8283}]},{"tag":"IGNORED2","segments2":[{"start":8694,"end":8722}]},{"tag":"IGNORED2","segments2":[{"start":9373,"end":9389}]},{"tag":"IGNORED2","segments2":[{"start":9446,"end":9476}]},{"tag":"IGNORED2","segments2":[{"start":9830,"end":9858}]},{"tag":"IGNORED2","segments2":[{"start":10274,"end":10296}]},{"tag":"IGNORED2","segments2":[{"start":11123,"end":11147}]},{"tag":"IGNORED2","segments2":[{"start":11447,"end":11484}]},{"tag":"IGNORED2","segments2":[{"start":11582,"end":11610}]},{"tag":"IGNORED2","segments2":[{"start":12475,"end":12485}]},{"tag":"IGNORED2","segments2":[{"start":13508,"end":13552}]},{"tag":"IGNORED2","segments2":[{"start":13773,"end":13789}]},{"tag":"IGNORED2","segments2":[{"start":14400,"end":14422}]},{"tag":"IGNORED2","segments2":[{"start":14627,"end":14657}]},{"tag":"IGNORED2","segments2":[{"start":15003,"end":15031}]},{"tag":"IGNORED2","segments2":[{"start":15447,"end":15469}]},{"tag":"IGNORED2","segments2":[{"start":16157,"end":16181}]},{"tag":"IGNORED2","segments2":[{"start":16481,"end":16518}]},{"tag":"IGNORED2","segments2":[{"start":16616,"end":16644}]},{"tag":"IGNORED2","segments2":[{"start":17824,"end":17834}]},{"tag":"IGNORED2","segments2":[{"start":18792,"end":18836}]},{"tag":"IGNORED2","segments2":[{"start":19057,"end":19073}]},{"tag":"IGNORED2","segments2":[{"start":19412,"end":19434}]},{"tag":"IGNORED2","segments2":[{"start":19717,"end":19760}]},{"tag":"IGNORED2","segments2":[{"start":21246,"end":21273}]},{"tag":"IGNORED2","segments2":[{"start":24267,"end":24278}]},{"tag":"IGNORED2","segments2":[{"start":24483,"end":24516}]},{"tag":"IGNORED2","segments2":[{"start":24670,"end":24728}]},{"tag":"IGNORED2","segments2":[{"start":24843,"end":24867}]},{"tag":"IGNORED2","segments2":[{"start":25120,"end":25145}]},{"tag":"ALIGN","line1":1,"line2":1},{"tag":"ALIGN","line1":3,"line2":3,"ext":11},{"tag":"ALIGN","line1":16,"line2":16,"ext":20},{"tag":"ALIGN","line1":38,"line2":38},{"tag":"ALIGN","line1":40,"line2":40},{"tag":"ALIGN","line1":42,"line2":42,"ext":2},{"tag":"ALIGN","line1":46,"line2":46},{"tag":"ALIGN","line1":48,"line2":48,"ext":2},{"tag":"ALIGN","line1":53,"line2":53,"ext":2},{"tag":"ALIGN","line1":58,"line2":58,"ext":3},{"tag":"ALIGN","line1":63,"line2":63},{"tag":"ALIGN","line1":66,"line2":66,"ext":2},{"tag":"ALIGN","line1":70,"line2":70,"ext":1},{"tag":"ALIGN","line1":74,"line2":74,"ext":1},{"tag":"ALIGN","line1":77,"line2":77,"ext":5},{"tag":"ALIGN","line1":84,"line2":84},{"tag":"ALIGN","line1":88,"line2":88,"ext":2},{"tag":"ALIGN","line1":92,"line2":92,"ext":1},{"tag":"ALIGN","line1":96,"line2":96,"ext":4},{"tag":"ALIGN","line1":102,"line2":102,"ext":4},{"tag":"ALIGN","line1":110,"line2":110,"ext":10},{"tag":"ALIGN","line1":122,"line2":122},{"tag":"ALIGN","line1":124,"line2":124},{"tag":"ALIGN","line1":128,"line2":128,"ext":2},{"tag":"ALIGN","line1":132,"line2":132,"ext":1},{"tag":"ALIGN","line1":136,"line2":136,"ext":1},{"tag":"ALIGN","line1":139,"line2":139,"ext":4},{"tag":"ALIGN","line1":147,"line2":147,"ext":10},{"tag":"ALIGN","line1":159,"line2":159},{"tag":"ALIGN","line1":161,"line2":161},{"tag":"ALIGN","line1":165,"line2":165,"ext":2},{"tag":"ALIGN","line1":169,"line2":169,"ext":1},{"tag":"ALIGN","line1":173,"line2":173,"ext":1},{"tag":"ALIGN","line1":176,"line2":176,"ext":5},{"tag":"ALIGN","line1":183,"line2":183},{"tag":"ALIGN","line1":187,"line2":187,"ext":2},{"tag":"ALIGN","line1":191,"line2":191,"ext":1},{"tag":"ALIGN","line1":195,"line2":195,"ext":1},{"tag":"ALIGN","line1":198,"line2":198,"ext":7},{"tag":"ALIGN","line1":207,"line2":207},{"tag":"ALIGN","line1":212,"line2":212,"ext":2},{"tag":"ALIGN","line1":216,"line2":216,"ext":1},{"tag":"ALIGN","line1":220,"line2":220,"ext":1},{"tag":"ALIGN","line1":223,"line2":223,"ext":2},{"tag":"ALIGN","line1":228,"line2":228},{"tag":"ALIGN","line1":230,"line2":230,"ext":1},{"tag":"ALIGN","line1":233,"line2":233,"ext":4},{"tag":"ALIGN","line1":240,"line2":240},{"tag":"ALIGN","line1":242,"line2":242,"ext":2},{"tag":"ALIGN","line1":246,"line2":246,"ext":1},{"tag":"ALIGN","line1":249,"line2":249},{"tag":"ALIGN","line1":252,"line2":252,"ext":10},{"tag":"ALIGN","line1":264,"line2":264},{"tag":"ALIGN","line1":266,"line2":266,"ext":1},{"tag":"ALIGN","line1":271,"line2":271,"ext":3},{"tag":"ALIGN","line1":280,"line2":280},{"tag":"ALIGN","line1":282,"line2":282,"ext":1},{"tag":"ALIGN","line1":285,"line2":285},{"tag":"ALIGN","line1":287,"line2":287,"ext":6},{"tag":"ALIGN","line1":296,"line2":296},{"tag":"ALIGN","line1":298,"line2":298},{"tag":"ALIGN","line1":300,"line2":300,"ext":2},{"tag":"ALIGN","line1":304,"line2":304,"ext":3},{"tag":"ALIGN","line1":313,"line2":313,"ext":1},{"tag":"ALIGN","line1":316,"line2":316,"ext":3},{"tag":"ALIGN","line1":322,"line2":322,"ext":2},{"tag":"ALIGN","line1":326,"line2":326},{"tag":"ALIGN","line1":331,"line2":331,"ext":2},{"tag":"ALIGN","line1":335,"line2":335,"ext":1},{"tag":"ALIGN","line1":339,"line2":339,"ext":1},{"tag":"ALIGN","line1":342,"line2":342,"ext":2},{"tag":"ALIGN","line1":347,"line2":347},{"tag":"ALIGN","line1":349,"line2":349,"ext":5},{"tag":"ALIGN","line1":357,"line2":357},{"tag":"ALIGN","line1":359,"line2":359,"ext":2},{"tag":"ALIGN","line1":363,"line2":363,"ext":1},{"tag":"ALIGN","line1":366,"line2":366},{"tag":"ALIGN","line1":369,"line2":369,"ext":3},{"tag":"ALIGN","line1":374,"line2":374,"ext":9},{"tag":"ALIGN","line1":385,"line2":385,"ext":1},{"tag":"ALIGN","line1":390,"line2":390,"ext":1},{"tag":"ALIGN","line1":397,"line2":397},{"tag":"ALIGN","line1":399,"line2":399,"ext":1},{"tag":"ALIGN","line1":402,"line2":402},{"tag":"ALIGN","line1":404,"line2":404,"ext":6},{"tag":"ALIGN","line1":413,"line2":413},{"tag":"ALIGN","line1":415,"line2":415},{"tag":"ALIGN","line1":417,"line2":417,"ext":2},{"tag":"ALIGN","line1":421,"line2":421,"ext":3},{"tag":"ALIGN","line1":430,"line2":430,"ext":1},{"tag":"ALIGN","line1":434,"line2":434,"ext":2},{"tag":"ALIGN","line1":438,"line2":438},{"tag":"ALIGN","line1":442,"line2":442},{"tag":"ALIGN","line1":445,"line2":445,"ext":6},{"tag":"ALIGN","line1":454,"line2":454,"ext":13},{"tag":"ALIGN","line1":473,"line2":473,"ext":1},{"tag":"ALIGN","line1":478,"line2":478,"ext":2},{"tag":"ALIGN","line1":483,"line2":483,"ext":2},{"tag":"ALIGN","line1":487,"line2":487,"ext":1},{"tag":"ALIGN","line1":491,"line2":491,"ext":1},{"tag":"ALIGN","line1":495,"line2":495,"ext":4},{"tag":"ALIGN","line1":501,"line2":501,"ext":3},{"tag":"ALIGN","line1":506,"line2":506,"ext":3},{"tag":"ALIGN","line1":514,"line2":514,"ext":5},{"tag":"ALIGN","line1":521,"line2":521,"ext":3},{"tag":"ALIGN","line1":526,"line2":526,"ext":1},{"tag":"ALIGN","line1":529,"line2":529},{"tag":"ALIGN","line1":531,"line2":531,"ext":6},{"tag":"ALIGN","line1":540,"line2":540,"ext":1},{"tag":"ALIGN","line1":544,"line2":544,"ext":1},{"tag":"ALIGN","line1":547,"line2":547},{"tag":"ALIGN","line1":549,"line2":549,"ext":4},{"tag":"ALIGN","line1":558,"line2":558,"ext":1},null]