[{"tag":"DELETE","start1":75,"end1":102,"segments1":[{"start":75,"end":78},{"start":102,"end":102}]},{"tag":"DELETE","start1":56,"end1":69,"segments1":[{"start":56,"end":69}]},{"tag":"RELABEL","start1":42,"end1":46,"segments1":[{"start":42,"end":46}],"start2":44,"end2":58,"segments2":[{"start":44,"end":58}]},{"tag":"INSERT","start2":73,"end2":103,"segments2":[{"start":73,"end":79},{"start":103,"end":103}]},{"tag":"RELABEL","start1":100,"end1":100,"segments1":[{"start":100,"end":100}],"start2":101,"end2":101,"segments2":[{"start":101,"end":101}]},{"tag":"INSERT","start2":60,"end2":64,"segments2":[{"start":60,"end":64}]},{"tag":"RELABEL","start1":37,"end1":40,"segments1":[{"start":37,"end":40}],"start2":40,"end2":42,"segments2":[{"start":40,"end":42}]},{"tag":"RELABEL","start1":30,"end1":35,"segments1":[{"start":30,"end":35}],"start2":30,"end2":38,"segments2":[{"start":30,"end":38}]},{"tag":"ALIGN","line1":1,"line2":1,"ext":1},{"tag":"ALIGN","line1":4,"line2":4,"ext":1},{"tag":"ALIGN","line1":7,"line2":6},null]