{"https://github.com/nasa/mct": [{"time": 2.8571362495422363, "effort": 391, "similarity": 0.9135147091351471, "distance": 0.1893462469733656, "effort2": 16, "similarity2": 0.9929676511954993, "distance2": 0.00903954802259887, "parsable_merge": true, "effort3": 621, "similarity3": 0.7689161554192229, "distance3": 0.5339638865004299, "extra_order": 0, "extra_ins": 0, "missed_ins": 0, "ins_size": 474, "missed_map": 0, "map_error": 0, "map_size": 1153, "missed_del": 0, "del_size": 0, "id": 15}], "https://github.com/voldemort/voldemort": [{"time": 2.660862445831299, "effort": 426, "similarity": 0.8973988439306358, "distance": 0.2286634460547504, "effort2": 0, "similarity2": 1.0, "distance2": 0.0, "parsable_merge": true, "effort3": 258, "similarity3": 0.8996617812852311, "distance3": 0.21428571428571427, "extra_order": 0, "extra_ins": 0, "missed_ins": 0, "ins_size": 211, "missed_map": 0, "map_error": 0, "map_size": 1197, "missed_del": 0, "del_size": 0, "id": 17}, {"time": 2.3241426944732666, "effort": 2358, "similarity": 0.09307692307692307, "distance": 19.487603305785125, "effort2": 1, "similarity2": 0.9994895354772844, "distance2": 0.0010214504596527069, "parsable_merge": true, "effort3": 145, "similarity3": 0.9089912280701754, "distance3": 0.1724137931034483, "extra_order": 0, "extra_ins": 0, "missed_ins": 0, "ins_size": 115, "missed_map": 0, "map_error": 0, "map_size": 840, "missed_del": 0, "del_size": 8, "id": 75}, {"time": 1.1153149604797363, "hunk_conflict_count": 1, "effort": 3, "similarity": 0.9473684210526315, "distance": 0.1111111111111111, "effort2": 2, "similarity2": 0.95, "distance2": 0.10526315789473684, "parsable_merge": true, "id": 241}], "https://github.com/rzwitserloot/lombok": [{"time": 3.7773196697235107, "effort": 12, "similarity": 0.998282770463652, "distance": 0.0034403669724770644, "effort2": 0, "similarity2": 1.0, "distance2": 0.0, "parsable_merge": true, "effort3": 26, "similarity3": 0.9913598797896318, "distance3": 0.009792843691148776, "extra_order": 0, "extra_ins": 0, "missed_ins": 0, "ins_size": 7, "missed_map": 0, "map_error": 0, "map_size": 2654, "missed_del": 0, "del_size": 12, "id": 22}], "https://github.com/yusuke/twitter4j": [{"time": 1.4945950508117676, "effort": 370, "similarity": 0.4444444444444444, "distance": 2.5, "effort2": 0, "similarity2": 1.0, "distance2": 0.0, "parsable_merge": true, "effort3": 180, "similarity3": 0.43478260869565216, "distance3": 2.5, "extra_order": 0, "extra_ins": 0, "missed_ins": 0, "ins_size": 155, "missed_map": 0, "map_error": 0, "map_size": 72, "missed_del": 0, "del_size": 0, "id": 11}]}