[{"tag":"INSERT","start2":6303,"end2":6376,"segments2":[{"start":6303,"end":6347}]},{"tag":"INSERT","start2":861,"end2":911,"segments2":[{"start":861,"end":911}]},{"tag":"IGNORED1","segments1":[{"start":0,"end":599}]},{"tag":"IGNORED1","segments1":[{"start":932,"end":992}]},{"tag":"IGNORED1","segments1":[{"start":7307,"end":7373}]},{"tag":"IGNORED1","segments1":[{"start":7385,"end":7395}]},{"tag":"IGNORED1","segments1":[{"start":7820,"end":7885}]},{"tag":"IGNORED1","segments1":[{"start":7897,"end":7931}]},{"tag":"IGNORED2","segments2":[{"start":0,"end":599}]},{"tag":"IGNORED2","segments2":[{"start":984,"end":1044}]},{"tag":"IGNORED2","segments2":[{"start":7415,"end":7481}]},{"tag":"IGNORED2","segments2":[{"start":7493,"end":7503}]},{"tag":"IGNORED2","segments2":[{"start":7928,"end":7993}]},{"tag":"IGNORED2","segments2":[{"start":8005,"end":8039}]},{"tag":"ALIGN","line1":17,"line2":17},{"tag":"ALIGN","line1":19,"line2":19,"ext":2},{"tag":"ALIGN","line1":23,"line2":23,"ext":2},{"tag":"ALIGN","line1":26,"line2":27},{"tag":"ALIGN","line1":28,"line2":29},{"tag":"ALIGN","line1":35,"line2":36},{"tag":"ALIGN","line1":37,"line2":38},{"tag":"ALIGN","line1":39,"line2":40,"ext":23},{"tag":"ALIGN","line1":64,"line2":65,"ext":48},{"tag":"ALIGN","line1":115,"line2":116,"ext":4},{"tag":"ALIGN","line1":121,"line2":122,"ext":3},{"tag":"ALIGN","line1":126,"line2":127,"ext":4},{"tag":"ALIGN","line1":132,"line2":133,"ext":4},{"tag":"ALIGN","line1":139,"line2":140,"ext":1},{"tag":"ALIGN","line1":142,"line2":144},{"tag":"ALIGN","line1":142,"line2":143},{"tag":"ALIGN","line1":144,"line2":146,"ext":1},{"tag":"ALIGN","line1":147,"line2":149,"ext":1},{"tag":"ALIGN","line1":150,"line2":152,"ext":3},{"tag":"ALIGN","line1":155,"line2":157,"ext":2},{"tag":"ALIGN","line1":160,"line2":162,"ext":2},{"tag":"ALIGN","line1":167,"line2":169,"ext":4},{"tag":"ALIGN","line1":176,"line2":178,"ext":4},{"tag":"ALIGN","line1":183,"line2":185,"ext":4},{"tag":"ALIGN","line1":192,"line2":194,"ext":1},{"tag":"ALIGN","line1":196,"line2":198,"ext":1},{"tag":"ALIGN","line1":200,"line2":202,"ext":1},{"tag":"ALIGN","line1":204,"line2":206,"ext":1},{"tag":"ALIGN","line1":208,"line2":210,"ext":1},{"tag":"ALIGN","line1":212,"line2":214,"ext":1},{"tag":"ALIGN","line1":216,"line2":218,"ext":1},{"tag":"ALIGN","line1":220,"line2":222,"ext":1},{"tag":"ALIGN","line1":224,"line2":226,"ext":1},{"tag":"ALIGN","line1":228,"line2":230,"ext":1},{"tag":"ALIGN","line1":232,"line2":234,"ext":1},{"tag":"ALIGN","line1":236,"line2":238,"ext":1},{"tag":"ALIGN","line1":240,"line2":242,"ext":1},{"tag":"ALIGN","line1":244,"line2":246,"ext":1},{"tag":"ALIGN","line1":248,"line2":250,"ext":1},{"tag":"ALIGN","line1":252,"line2":254,"ext":1},{"tag":"ALIGN","line1":256,"line2":258,"ext":1},{"tag":"ALIGN","line1":260,"line2":262,"ext":1},{"tag":"ALIGN","line1":264,"line2":266,"ext":1},{"tag":"ALIGN","line1":268,"line2":270,"ext":1},{"tag":"ALIGN","line1":272,"line2":274,"ext":1},{"tag":"ALIGN","line1":276,"line2":278,"ext":1},{"tag":"ALIGN","line1":280,"line2":282,"ext":1},{"tag":"ALIGN","line1":284,"line2":286,"ext":1},{"tag":"ALIGN","line1":288,"line2":290,"ext":1},{"tag":"ALIGN","line1":292,"line2":294,"ext":1},{"tag":"ALIGN","line1":296,"line2":298,"ext":1},{"tag":"ALIGN","line1":300,"line2":302,"ext":1},{"tag":"ALIGN","line1":304,"line2":306,"ext":1},{"tag":"ALIGN","line1":308,"line2":310,"ext":1},{"tag":"ALIGN","line1":312,"line2":314,"ext":1},{"tag":"ALIGN","line1":316,"line2":318,"ext":1},{"tag":"ALIGN","line1":320,"line2":322,"ext":1},{"tag":"ALIGN","line1":324,"line2":326,"ext":1},{"tag":"ALIGN","line1":328,"line2":330,"ext":1},{"tag":"ALIGN","line1":332,"line2":334,"ext":7},{"tag":"ALIGN","line1":341,"line2":343,"ext":33},{"tag":"ALIGN","line1":377,"line2":379,"ext":28},{"tag":"ALIGN","line1":408,"line2":410,"ext":17},null]