[{"tag":"DELETE","start1":8399,"end1":8452,"segments1":[{"start":8399,"end":8449},{"start":8451,"end":8452}]},{"tag":"DELETE","start1":1200,"end1":1236,"segments1":[{"start":1200,"end":1236}]},{"tag":"DELETE","start1":1164,"end1":1198,"segments1":[{"start":1164,"end":1198}]},{"tag":"DELETE","start1":1085,"end1":1123,"segments1":[{"start":1085,"end":1123}]},{"tag":"INSERT","start2":8885,"end2":9191,"segments2":[{"start":8885,"end":8902},{"start":8978,"end":9191}]},{"tag":"RELABEL","start1":8552,"end1":8625,"segments1":[{"start":8560,"end":8564},{"start":8625,"end":8625}],"start2":8903,"end2":8977,"segments2":[{"start":8911,"end":8915}]},{"tag":"RELABEL","start1":8570,"end1":8597,"segments1":[{"start":8570,"end":8581}],"start2":8921,"end2":8950,"segments2":[{"start":8921,"end":8934}]},{"tag":"RELABEL","start1":8527,"end1":8540,"segments1":[{"start":8527,"end":8540}],"start2":8873,"end2":8873,"segments2":[{"start":8873,"end":8873}]},{"tag":"RELABEL","start1":8502,"end1":8525,"segments1":[{"start":8502,"end":8509}],"start2":8843,"end2":8871,"segments2":[{"start":8843,"end":8855}]},{"tag":"RELABEL","start1":8462,"end1":8485,"segments1":[{"start":8462,"end":8469}],"start2":8798,"end2":8826,"segments2":[{"start":8798,"end":8810}]},{"tag":"INSERT","start2":8748,"end2":8788,"segments2":[{"start":8749,"end":8788}]},{"tag":"INSERT","start2":8655,"end2":8738,"segments2":[{"start":8655,"end":8738}]},{"tag":"RELABEL","start1":8322,"end1":8389,"segments1":[{"start":8323,"end":8334},{"start":8389,"end":8389}],"start2":8564,"end2":8645,"segments2":[{"start":8565,"end":8568},{"start":8645,"end":8645}]},{"tag":"RELABEL","start1":8356,"end1":8387,"segments1":[{"start":8356,"end":8387}],"start2":8588,"end2":8643,"segments2":[{"start":8588,"end":8643}]},{"tag":"RELABEL","start1":8336,"end1":8353,"segments1":[{"start":8336,"end":8353}],"start2":8570,"end2":8585,"segments2":[{"start":8570,"end":8585}]},{"tag":"RELABEL","start1":8239,"end1":8312,"segments1":[{"start":8240,"end":8251},{"start":8312,"end":8312}],"start2":8492,"end2":8554,"segments2":[{"start":8493,"end":8496},{"start":8554,"end":8554}]},{"tag":"RELABEL","start1":8253,"end1":8274,"segments1":[{"start":8253,"end":8274}],"start2":8498,"end2":8516,"segments2":[{"start":8498,"end":8516}]},{"tag":"INSERT","start2":8464,"end2":8482,"segments2":[{"start":8464,"end":8482}]},{"tag":"RELABEL","start1":5146,"end1":5166,"segments1":[{"start":5152,"end":5166}],"start2":5371,"end2":5392,"segments2":[{"start":5377,"end":5392}]},{"tag":"RELABEL","start1":4875,"end1":4900,"segments1":[{"start":4888,"end":4898}],"start2":5098,"end2":5125,"segments2":[{"start":5111,"end":5123}]},{"tag":"RELABEL","start1":4662,"end1":4682,"segments1":[{"start":4668,"end":4682}],"start2":4884,"end2":4905,"segments2":[{"start":4890,"end":4905}]},{"tag":"INSERT","start2":1773,"end2":1852,"segments2":[{"start":1773,"end":1852}]},{"tag":"INSERT","start2":1706,"end2":1736,"segments2":[{"start":1706,"end":1736}]},{"tag":"INSERT","start2":1681,"end2":1704,"segments2":[{"start":1681,"end":1704}]},{"tag":"INSERT","start2":1366,"end2":1389,"segments2":[{"start":1366,"end":1389}]},{"tag":"INSERT","start2":1237,"end2":1292,"segments2":[{"start":1237,"end":1292}]},{"tag":"INSERT","start2":1180,"end2":1235,"segments2":[{"start":1180,"end":1235}]},{"tag":"INSERT","start2":1124,"end2":1178,"segments2":[{"start":1124,"end":1178}]},{"tag":"IGNORED1","segments1":[{"start":0,"end":801}]},{"tag":"IGNORED2","segments2":[{"start":0,"end":801}]},{"tag":"ALIGN","line1":18,"line2":18},{"tag":"ALIGN","line1":20,"line2":20,"ext":5},{"tag":"ALIGN","line1":27,"line2":26},{"tag":"ALIGN","line1":30,"line2":30,"ext":2},{"tag":"ALIGN","line1":33,"line2":34},{"tag":"ALIGN","line1":35,"line2":36,"ext":1},{"tag":"ALIGN","line1":38,"line2":39,"ext":3},{"tag":"ALIGN","line1":43,"line2":45},{"tag":"ALIGN","line1":45,"line2":48,"ext":3},{"tag":"ALIGN","line1":50,"line2":53,"ext":7},{"tag":"ALIGN","line1":60,"line2":63,"ext":3},{"tag":"ALIGN","line1":67,"line2":70,"ext":2},{"tag":"ALIGN","line1":72,"line2":75,"ext":8},{"tag":"ALIGN","line1":84,"line2":87,"ext":8},{"tag":"ALIGN","line1":95,"line2":98,"ext":4},{"tag":"ALIGN","line1":102,"line2":105,"ext":6},{"tag":"ALIGN","line1":111,"line2":114,"ext":7},{"tag":"ALIGN","line1":121,"line2":124,"ext":7},{"tag":"ALIGN","line1":131,"line2":134,"ext":3},{"tag":"ALIGN","line1":137,"line2":140,"ext":10},{"tag":"ALIGN","line1":151,"line2":154,"ext":3},{"tag":"ALIGN","line1":157,"line2":160,"ext":9},{"tag":"ALIGN","line1":170,"line2":173,"ext":2},{"tag":"ALIGN","line1":175,"line2":178,"ext":6},{"tag":"ALIGN","line1":186,"line2":188,"ext":1},{"tag":"ALIGN","line1":190,"line2":192,"ext":1},{"tag":"ALIGN","line1":194,"line2":196,"ext":1},{"tag":"ALIGN","line1":196,"line2":199,"ext":1},{"tag":"ALIGN","line1":198,"line2":202,"ext":1},{"tag":"ALIGN","line1":200,"line2":205},{"tag":"ALIGN","line1":204,"line2":214,"ext":2},{"tag":"ALIGN","line1":209,"line2":219,"ext":2},{"tag":"ALIGN","line1":214,"line2":224,"ext":2},{"tag":"ALIGN","line1":220,"line2":230,"ext":4},{"tag":"ALIGN","line1":228,"line2":238,"ext":5},{"tag":"ALIGN","line1":236,"line2":246,"ext":3},null]