{"https://github.com/google/ExoPlayer": [{"time": 10.979887962341309, "effort": 74, "similarity": 0.9903090623363018, "distance": 0.01957154192012695, "effort2": 46, "similarity2": 0.9868819374369324, "distance2": 0.015572105619498984, "parsable_merge": true, "effort3": 259, "similarity3": 0.9173288250211327, "distance3": 0.09011830201809325, "extra_order": 0, "extra_ins": 0, "missed_ins": 0, "ins_size": 74, "missed_map": 0, "map_error": 0, "map_size": 2828, "missed_del": 0, "del_size": 13, "id": 58}]}