{"https://github.com/apache/cassandra": [{"time": 0, "effort": 0, "similarity": 1.0, "distance": 0.0, "effort2": 0, "similarity2": 1.0, "distance2": 0.0, "parsable_merge": true, "effort3": 599, "similarity3": 0.8718120057912908, "distance3": 0.1415406427221172, "extra_order": 0, "extra_ins": 0, "missed_ins": 2, "ins_size": 194, "missed_map": 0, "map_error": 0, "map_size": 4166, "missed_del": 0, "del_size": 75, "id": 655}, {"time": 0, "effort": 0, "similarity": 1.0, "distance": 0.0, "effort2": 0, "similarity2": 1.0, "distance2": 0.0, "parsable_merge": true, "effort3": 471, "similarity3": 0.7874476987447698, "distance3": 0.48757763975155277, "extra_order": 0, "extra_ins": 0, "missed_ins": 0, "ins_size": 382, "missed_map": 0, "map_error": 0, "map_size": 953, "missed_del": 0, "del_size": 14, "id": 90}, {"time": 0, "effort": 0, "similarity": 1.0, "distance": 0.0, "effort2": 0, "similarity2": 1.0, "distance2": 0.0, "parsable_merge": true, "effort3": 37, "similarity3": 0.9866276640200585, "distance3": 0.015494137353433836, "extra_order": 0, "extra_ins": 0, "missed_ins": 0, "ins_size": 9, "missed_map": 0, "map_error": 0, "map_size": 2385, "missed_del": 0, "del_size": 28, "id": 36}, {"time": 0, "effort": 0, "similarity": 1.0, "distance": 0.0, "effort2": 0, "similarity2": 1.0, "distance2": 0.0, "parsable_merge": true, "effort3": 88, "similarity3": 0.8345864661654135, "distance3": 0.3963963963963964, "extra_order": 0, "extra_ins": 0, "missed_ins": 1, "ins_size": 65, "missed_map": 0, "map_error": 0, "map_size": 222, "missed_del": 0, "del_size": 0, "id": 231}, {"time": 0, "effort": 0, "similarity": 1.0, "distance": 0.0, "effort2": 0, "similarity2": 1.0, "distance2": 0.0, "parsable_merge": true, "effort3": 37, "similarity3": 0.8471337579617835, "distance3": 0.2569444444444444, "extra_order": 0, "extra_ins": 0, "missed_ins": 0, "ins_size": 18, "missed_map": 0, "map_error": 0, "map_size": 143, "missed_del": 0, "del_size": 15, "id": 282}], "https://github.com/deeplearning4j/deeplearning4j": [{"time": 0, "effort": 0, "similarity": 1.0, "distance": 0.0, "effort2": 0, "similarity2": 1.0, "distance2": 0.0, "parsable_merge": true, "effort3": 128, "similarity3": 0.9155509783728115, "distance3": 0.13867822318526543, "extra_order": 0, "extra_ins": 0, "missed_ins": 0, "ins_size": 76, "missed_map": 0, "map_error": 0, "map_size": 911, "missed_del": 0, "del_size": 18, "id": 19}]}